ipp_toolkit/__init__.py
ipp_toolkit/config.py
ipp_toolkit/data/__init__.py
ipp_toolkit/data/data.py
ipp_toolkit/data/domain_data.py
ipp_toolkit/data/masked_labeled_image.py
ipp_toolkit/data/random_2d.py
ipp_toolkit/data/structured_2d.py
ipp_toolkit/experiments/MCTS.py
ipp_toolkit/experiments/__init__.py
ipp_toolkit/experiments/comparing_ipp_approaches.py
ipp_toolkit/experiments/missions.py
ipp_toolkit/experiments/noise_modeling.py
ipp_toolkit/experiments/point_sampler.py
ipp_toolkit/experiments/sensor_error.py
ipp_toolkit/planners/MCTS_planner.py
ipp_toolkit/planners/RAPTORS_planner.py
ipp_toolkit/planners/__init__.py
ipp_toolkit/planners/candidate_location_selector.py
ipp_toolkit/planners/classical_GP_planners.py
ipp_toolkit/planners/diversity_planner.py
ipp_toolkit/planners/masked_planner.py
ipp_toolkit/planners/planners.py
ipp_toolkit/planners/samplers.py
ipp_toolkit/planners/utils.py
ipp_toolkit/predictors/__init__.py
ipp_toolkit/predictors/convenient_predictors.py
ipp_toolkit/predictors/convolutional_predictors.py
ipp_toolkit/predictors/intrestingness_computers.py
ipp_toolkit/predictors/masked_image_predictor.py
ipp_toolkit/predictors/pytorch_predictor.py
ipp_toolkit/predictors/uncertain_predictors.py
ipp_toolkit/sensors/__init__.py
ipp_toolkit/sensors/sensors.py
ipp_toolkit/trainers/gaussian_process.py
ipp_toolkit/trainers/model_based/MPC_policy.py
ipp_toolkit/trainers/model_based/base_agent.py
ipp_toolkit/trainers/model_based/base_model.py
ipp_toolkit/trainers/model_based/base_policy.py
ipp_toolkit/trainers/model_based/ff_model.py
ipp_toolkit/trainers/model_based/logger.py
ipp_toolkit/trainers/model_based/mb_agent.py
ipp_toolkit/trainers/model_based/pytorch_util.py
ipp_toolkit/trainers/model_based/replay_buffer.py
ipp_toolkit/trainers/model_based/rl_trainer.py
ipp_toolkit/trainers/model_based/utils.py
ipp_toolkit/utils/__init__.py
ipp_toolkit/utils/data/__init__.py
ipp_toolkit/utils/data/dvc.py
ipp_toolkit/utils/filenames.py
ipp_toolkit-0.1.2.dist-info/METADATA
ipp_toolkit-0.1.2.dist-info/WHEEL
ipp_toolkit-0.1.2.dist-info/RECORD
